latex_generator/__init__.py
latex_generator/latex_generation.py
itmo_latex_generator-0.2.dist-info/METADATA
itmo_latex_generator-0.2.dist-info/WHEEL
itmo_latex_generator-0.2.dist-info/top_level.txt
itmo_latex_generator-0.2.dist-info/RECORD
