Metadata-Version: 2.1
Name: itmo-latex-generator
Version: 0.2
Summary: ITMO 2025. A simple LaTeX generator for tables and images
Home-page: https://github.com/VoLuIcHiK/latex_generator_itmo
Author: Anastasiya Valueva
Author-email: valueva200211@gmail.com
License: UNKNOWN
Platform: UNKNOWN
